{
  "E1": "Recruit",
  "E2": "Operator",
  "E3": "Specialist",
  "E4": "Senior Operator",
  "E5": "Chief Operator",
  "E6": "Squad Leader",
  "E7": "Senior Squad Leader",
  "E8": "Platoon Leader",
  "E9": "Senior Platoon Leader",
  "T1": "Technical Officer",
  "T2": "Senior Technical Officer",
  "T3": "Lead Technical Officer",
  "T4": "Chief Technical Officer",
  "T5": "Master Technical Officer",
  "O1": "Field Commander",
  "O2": "Platoon Commander",
  "O3": "Company Commander",
  "O4": "Executive Commander",
  "O5": "Operations Commander",
  "O6": "Deputy Director of Operations",
  "O7": "Director of Operations",
  "O8": "Chief Executive Officer"
}
